{
    "title": "Stacktrace Podcast 059: “Bugs are people too”",
    "description": "John Sundell and Gui Rambo talk about using the iPad Pro for coding and presentations, cross-platform code and feature sharing, what's like to record podcasts in your non-native language and much more!",
    "url": "https://9to5mac.com/2019/10/23/stacktrace-podcast-059-bugs-are-people-too/",
    "curator": {
        "name": "Pedro Carrasco",
        "url": "https://twitter.com/pedrommcarrasco"
    },
    "tags": [
        "podcast"
    ]
}
