{
     "title": "Handling future cases of enums in libraries without binary stability concerns",
     "description": "Sergej Jaskiewicz proposes making “all public enums in non-resilient libraries non-frozen by default an allow authors of those libraries to mark their public enums @frozen to indicate that no new cases will be added“. What do you think?",
     "url": "https://forums.swift.org/t/pitch-handling-future-cases-of-enums-in-libraries-without-binary-stability-concerns/32026",
     "curator": {
         "name": "Irshad PC",
         "url": "https://twitter.com/_irshadpc"
     },
     "tags": [
         "evolution"
     ]
 }
